[{"title":"venüs neden ters yönde döner","content":"\n    ven&#xFC;s ,kad&#x131;n&#x131; temsil eder. tersli&#x11F;i bu y&#xFC;zdendir.\n  ","author":"deli dumrulun torunu","authorURL":"https://eksisozluk.com/biri/deli-dumrulun-torunu","entryURL":"https://eksisozluk.com/entry/41859532"},{"title":"kendine 3 el ateş et sana bir şey olmayacak","content":"\n    her &#xF6;l&#xFC;m erken &#xF6;l&#xFC;m de&#x11F;il demek ki. iyi bile ya&#x15F;am&#x131;&#x15F; bu kafayla.\n  ","author":"verflixt","authorURL":"https://eksisozluk.com/biri/verflixt","entryURL":"https://eksisozluk.com/entry/141376059"},{"title":"6 ağustos 2020 dolar kuru","content":"\n    allah kimseyi; &apos;gezi eylemleri&apos; s&#x131;ras&#x131;nda #dolar 1.88&apos;den 1.92&apos;ye &#xE7;&#x131;kt&#x131; diye &quot;ekonomiyi bat&#x131;rd&#x131;n&#x131;z&quot; diyecek kadar al&#xE7;ak; dolar 1.92&apos;den 7.30&apos;a &#xE7;&#x131;kt&#x131;&#x11F;&#x131; halde tek kelime etmeyecek kadar haysiyetsiz, &#x15F;erefsiz yapmas&#x131;n...<br><br>amin deyu verin bre m&#xFC;sl&#xFC;manlar.\n  ","author":"her biji recop wundebahg","authorURL":"https://eksisozluk.com/biri/her-biji-recop-wundebahg","entryURL":"https://eksisozluk.com/entry/111193923"},{"title":"esenler otogarı tuvaletinde yere düşmek","content":"\n    mikroplar taraf&#x131;ndan aya&#x11F;a kald&#x131;r&#x131;lmakla sonu&#xE7;lan&#x131;r. ge&#xE7;irdikleri mutasyondan dolay&#x131; &quot;abi iyi misin, bir &#x15F;eyin var m&#x131;?&quot; diye bile sorabilirler.\n  ","author":"cl juke","authorURL":"https://eksisozluk.com/biri/cl-juke","entryURL":"https://eksisozluk.com/entry/91563415"},{"title":"15 temmuz 2019 ekrem imamoğlu'nun yuhalanması","content":"\n    yuhalama de&#x11F;il, %10 fark girmi&#x15F; gibi an&#x131;rma eylemidir.\n  ","author":"zerdest","authorURL":"https://eksisozluk.com/biri/zerdest","entryURL":"https://eksisozluk.com/entry/92653967"},{"title":"kırmızı dudaklı yarasa balığı","content":"\n    bal&#x131;klar&#x131;n kezban&#x131;d&#x131;r.\n  ","author":"beetlejuicebeetlejuicebeetlejuice","authorURL":"https://eksisozluk.com/biri/beetlejuicebeetlejuicebeetlejuice","entryURL":"https://eksisozluk.com/entry/37316270"},{"title":"anne","content":"\n    rafa kald&#x131;raca&#x11F;&#x131; ti$&#xF6;rt&#xFC;n 3 o&#x11F;lundan hangisine ait oldu&#x11F;unu koklayarak anlayan muhte$em varl&#x131;k.cenneti paspas yapan ki$ilik.\n  ","author":"silmaril","authorURL":"https://eksisozluk.com/biri/silmaril","entryURL":"https://eksisozluk.com/entry/5324664"},{"title":"anne babanın mesleğini soran öğretmen","content":"\n    &#xF6;&#x11F;rencilik hayat&#x131;m boyunca, bilin&#xE7;alt&#x131;ma hep &quot;k&#xF6;t&#xFC;&quot; an&#x131;lar i&#x15F;lemi&#x15F; &#xF6;&#x11F;retmen tipi, z&#xE2;l&#x131;m.<br><br>eveeeeeet &#xE7;ocuklar, hadi birbirimizi tan&#x131;yal&#x131;m. &#xF6;nce ben kendimi tan&#x131;tay&#x131;m. ad&#x131;m alfa, soyad&#x131;m beta. gama y&#x131;ld&#x131;r bu mesle&#x11F;i s&#xFC;rd&#xFC;rmekteyim. &#xF6;n&#xFC;m&#xFC;zdeki bu bir y&#x131;l boyunca sizlerin epsilon bilgisi dersine girece&#x11F;im. umar&#x131;m g&#xFC;zel bir e&#x11F;itim-&#xF6;&#x11F;retim y&#x131;l&#x131; olur. <br><br>ben kendimi tan&#x131;tt&#x131;m, &#x15F;imdi s&#x131;ra sizde. ehi.<sup class=\"ab\"><a title=\"(bkz: japon anime g&#xFC;l&#xFC;&#x15F;&#xFC;)\" href=\"/?q=japon+anime+g%c3%bcl%c3%bc%c5%9f%c3%bc\" data-query=\"japon anime g&#xFC;l&#xFC;&#x15F;&#xFC;\">*</a></sup> isim-soyad ve anne-baba mesle&#x11F;ini s&#xF6;yleyin. sa&#x11F; ba&#x15F;tan ba&#x15F;la can&#x131;m. (g&#xF6;zl&#xFC;&#x11F;&#xFC;n &#xFC;zerinden bakmak s&#xFB;retiyle parma&#x11F;&#x131; ile kendisine g&#xF6;re s&#x131;n&#x131;f&#x131;n sol yan&#x131;n&#x131; i&#x15F;aret eder.)<br><br>k&#xFC;&#xE7;&#xFC;kken tabi insan anlam&#x131;yor, bu anne-baba mesle&#x11F;i s&#xF6;yletme merasiminin nedenini. sorunun alt&#x131;nda yatan psikoloji, &quot;&#xF6;&#x11F;renciyi tan&#x131;maya &#xE7;al&#x131;&#x15F;ma &#xE7;abas&#x131;&quot; olarak g&#xF6;r&#xFC;lebiliyor ufa&#x11F;&#x131;ken. fakat bu amat&#xF6;r eylemin sonu&#xE7;lar&#x131;, &#xF6;&#x11F;rencilerde derin izler b&#x131;rak&#x131;yor.<br><br>+ad&#x131;m delta, soyad&#x131;m zeta. babam &#xE7;ift&#xE7;i, annem ev han&#x131;m&#x131;.<br>-evet &#xE7;ocu&#x11F;um sen devam et.<br>+ad&#x131;m ita, soyad&#x131;m teta. babam mali m&#xFC;&#x15F;avir, annem &#xF6;&#x11F;retmen.<br>-aa, ne &#xF6;&#x11F;retmeni, nerede &#xE7;al&#x131;&#x15F;&#x131;yor?<br>+yota ilk &#xF6;&#x11F;retim okulunda, kappa bilgisi &#xF6;&#x11F;retmeni, &#xF6;rtmenim.<br>-tamam yavrum sen devam et.<br>+ad&#x131;m lamda, soyad&#x131;m omikron. babam vefat etti, annem ev han&#x131;m&#x131;...<br><br>bu muhtemel diyalogtan sonra, s&#x131;n&#x131;f sessizli&#x11F;e b&#xFC;r&#xFC;n&#xFC;r. &quot;muhtemel&quot;dir &#xE7;&#xFC;nk&#xFC;, her s&#x131;n&#x131;fta anne veya babas&#x131; vefa etmi&#x15F; bir &#xE7;ocu&#x11F;un olma ihtimali vard&#x131;r. olaya sadece &#xF6;l&#xFC;m sertli&#x11F;i ile bakmayal&#x131;m. her s&#x131;n&#x131;fta, toplum normlar&#x131; taraf&#x131;ndan &quot;utan&#x131;lcak&quot; alg&#x131;s&#x131; olu&#x15F;turan bir mesle&#x11F;i olan anne veya babaya sahip &#xF6;&#x11F;renci olabilir. &#xE7;ocuk ya&#x15F;ta al&#x131;n teri ile kazan&#x131;lan paran&#x131;n &#xF6;nemli oldu&#x11F;u, mesle&#x11F;in &#xE7;a&#x11F;r&#x131;&#x15F;t&#x131;rd&#x131;&#x11F;&#x131; imgenin &#xF6;nemli olmad&#x131;&#x11F;&#x131;n&#x131; ba&#x15F;kalar&#x131;na anlatamayabilirsin. ger&#xE7;i bunu ba&#x15F;kalar&#x131;na anlatmaya &#xE7;al&#x131;&#x15F;maya gerek yoktur fakat bu idrake varabilmek &#xE7;ocukken ger&#xE7;ekle&#x15F;meyebilir. <br><br>yeni &#xF6;&#x11F;retmen ya da hocayla tan&#x131;&#x15F;&#x131;lcak her sene ba&#x15F;&#x131; zul&#xFC;md&#xFC;r bu &#xE7;ocuklara. yetmezmi&#x15F; gibi o g&#xFC;n ilk dersine giren t&#xFC;m &#xF6;&#x11F;retmenler, s&#x131;n&#x131;ftaki &#xF6;&#x11F;rencilere anne-baba mesleklerini s&#xF6;yletir. bu yetim-&#xF6;ks&#xFC;z &#xE7;ocuklara bu ac&#x131;y&#x131; neden ya&#x15F;at&#x131;r bu &#xF6;&#x11F;retmenler? <br><br>acaba, s&#x131;n&#x131;fta &quot;arkas&#x131;&quot; g&#xFC;&#xE7;l&#xFC; &#xF6;&#x11F;renci var m&#x131; diye kontrol etme &#xE7;abas&#x131; m&#x131;d&#x131;r bu? yoksa veliler toplant&#x131;s&#x131;nda mesle&#x11F;ini bildi&#x11F;iniz ebeveyne, usul&#xFC;ne g&#xF6;re hareket edebilme &#xF6;n haz&#x131;rl&#x131;&#x11F;&#x131; m&#x131;d&#x131;r bu?<br><br>iyi niyetli yakla&#x15F;ay&#x131;m bir de. s&#x131;n&#x131;fta durumu iyi olmayan &#xF6;&#x11F;rencileri bulup onlara yard&#x131;m edebilme ya da ona g&#xF6;re davranabilmek i&#xE7;in yap&#x131;lan bir tarama m&#x131;d&#x131;r bu? e&#x11F;er &#xF6;yleyse, neden bu fecaat t&#xFC;m s&#x131;n&#x131;f&#x131;n g&#xF6;zleri &#xF6;n&#xFC;nde ger&#xE7;ekle&#x15F;tirilmektedir?<br><br>bu sorunun, &#xE7;ocuk ve s&#x131;n&#x131;f psikolojisi &#xFC;zerine etkileri detayl&#x131;ca d&#xFC;&#x15F;&#xFC;l&#xFC;melidir. fosille&#x15F;mi&#x15F; &#xF6;&#x11F;retmenlere belki durumun izhan&#x131; tebli&#x11F; edemeyiz fakat daha yeti&#x15F;tirece&#x11F;i y&#xFC;zlerce-binlerce &#xF6;&#x11F;renci olan gen&#xE7; &#xF6;&#x11F;retmenlerimiz, bu tehlikeyi idrak etmeliler.\n  ","author":"tek hortumlu fil","authorURL":"https://eksisozluk.com/biri/tek-hortumlu-fil","entryURL":"https://eksisozluk.com/entry/35655709"},{"title":"atatürk","content":"\n    (bkz: <a class=\"b\" href=\"/?q=mustafa+kemal+atat%c3%bcrk\">mustafa kemal atat&#xFC;rk</a>)\n  ","author":"ssgicyedip yukseljimi the kewlsaprophagistmorkukuletaliprensesali gelmatarama su koatlantisfair","authorURL":"https://eksisozluk.com/biri/ssg","entryURL":"https://eksisozluk.com/?q=atat%c3%bcrk"},{"title":"iranlı genç kıza polisin feci tesettür dayağı","content":"\n    en b&#xFC;y&#xFC;k <a class=\"b\" href=\"/?q=atat%c3%bcrk\">atat&#xFC;rk</a> hayran&#x131; kitlenin t&#xFC;rk kad&#x131;n&#x131; olmas&#x131; gereklili&#x11F;ini ispat eden &#xE7;a&#x11F;d&#x131;&#x15F;&#x131; hadise.\n  ","author":"yavruyumurta","authorURL":"https://eksisozluk.com/biri/yavruyumurta","entryURL":"https://eksisozluk.com/entry/91708503"},{"title":"spoiler","content":"\n    spoil eden ki$i/$ey.. (bkz: <a class=\"b\" href=\"/?q=spoil+etmek\">spoil etmek</a>)\n  ","author":"disqlockedreamerduburosrickaptanagonyx daemonchetespitfire","authorURL":"https://eksisozluk.com/biri/disq","entryURL":"https://eksisozluk.com/?q=spoiler"},{"title":"spoiler","content":"\n    spoil eden ki$i/$ey.. (bkz: <a class=\"b\" href=\"/?q=spoil+etmek\">spoil etmek</a>)\n  ","author":"disqlockedreamerduburosrickaptanagonyx daemonchetespitfire","authorURL":"https://eksisozluk.com/biri/disq","entryURL":"https://eksisozluk.com/?q=spoiler"},{"title":"game of thrones","content":"\n    --- <a class=\"b\" href=\"/?q=spoiler\">spoiler</a> ---<br><br>lady stark&apos;in turk oldugunu kanitlayan dizi olmustur kesinlikle.<br>kapi actiricam size bahanesiyle gitti ogluna kizina kismet buldu, evlendirdi, geri dondu. bu kadin sadece turk olabilir, iddia etmeyin.<br><br>--- <a class=\"b\" href=\"/?q=spoiler\">spoiler</a> ---\n  ","author":"archely","authorURL":"https://eksisozluk.com/biri/archely","entryURL":"https://eksisozluk.com/entry/24030258"},{"title":"acımasız gerçekler","content":"\n    bir ka&#xE7; g&#xFC;nd&#xFC;r wall&apos;umu sikip atan bir facebook uygulamas&#x131;. &apos;&apos;x ile beraber uyumak ister miydin? evet/hay&#x131;r&apos;&apos; gibi bir dolu sa&#xE7;ma sapan soru... millet de bunlar&#x131; deli gibi &#xE7;&#xF6;z&#xFC;yor.<br><br>ha e&#x11F;er bu uygulama sadece benim arkada&#x15F; &#xE7;evrem taraf&#x131;ndan kullan&#x131;l&#x131;yorsa, durum benim a&#xE7;&#x131;mdan &#xE7;ok &#xE7;ok daha vahim.<br><br>ne olur &apos;&apos;bizim de ba&#x15F;&#x131;m&#x131;zda bu bela var&apos;&apos; desin bir ka&#xE7; ki&#x15F;i.\n  ","author":"zerdestbir ben bir barcelona bir de kendimiki ayakli kedizackmhcrbunlar hep yalan dolanokurumokursunokuroblinaainscrutableleptine","authorURL":"https://eksisozluk.com/biri/zerdest","entryURL":"https://eksisozluk.com/?q=ac%c4%b1mas%c4%b1z+ger%c3%a7ekler"},{"title":"ninja kaplumbağa pizzası","content":"\n    eve gelip a&#xE7; oldu&#x11F;unuzu farkedersiniz ulan ne yesem diye d&#xFC;&#x15F;&#xFC;n&#xFC;rken pizza s&#xF6;ylemek akl&#x131;n&#x131;za gelir. annenize fikri sundu&#x11F;unuzda aaa o&#x11F;lum ne gerek var para harcamaya ben yapar&#x131;m diye cevap verir . iyi dersiniz sonras&#x131;nda ninja kaplumba&#x11F;alar&#x131;n yedi&#x11F;i cinsten bir pizza hayal ederken ac&#x131; ger&#xE7;e&#x11F;in y&#xFC;z&#xFC;n&#xFC;ze tokat gibi vurmas&#x131;yla uyan&#x131;rs&#x131;n&#x131;z.<br><br>(bkz: <a class=\"b\" href=\"/?q=ac%c4%b1mas%c4%b1z+ger%c3%a7ekler\">ac&#x131;mas&#x131;z ger&#xE7;ekler</a>) <br><br><a rel=\"nofollow noopener\" class=\"url\" target=\"_blank\" href=\"http://www.facebook.com/photo.php?fbid=10150100558751456&amp;set=a.217837021455.145118.17900841455&amp;type=1\" title=\"http://www.facebook.com/photo.php?fbid=10150100558751456&amp;set=a.217837021455.145118.17900841455&amp;type=1\">http://www.facebook.com/&#x2026;.145118.17900841455&amp;type=1</a>\n  ","author":"caliterra","authorURL":"https://eksisozluk.com/biri/caliterra","entryURL":"https://eksisozluk.com/entry/23298825"}]